[
  {
    "filename": "2023年北京市中考道德与法治真题（空白卷）.docx",
    "subject": "政治",
    "year": 2023,
    "questions": [
      {
        "title": "1．本试卷共8页，共两部分，共20题，满分70分。考试时间70分钟。",
        "content": []
      },
      {
        "title": "2．在试卷和草稿纸上准确填写姓名、准考证号、考场号和座位号。",
        "content": []
      },
      {
        "title": "3．试题答案一律填涂或书写在答题卡上，在试卷上作答无效。",
        "content": []
      },
      {
        "title": "4．在答题卡上，选择题用2B铅笔作答，其他试题用黑色字迹签字笔作答。",
        "content": []
      },
      {
        "title": "5．考试结束，将本试卷、答题卡和草稿纸一并交回。",
        "content": [
          "第一部分",
          "本部分共15题，每题2分，共30分。在每题列出的四个选项中，选出最符合题目要求的一项。"
        ]
      },
      {
        "title": "1. 中国共产党第二十次全国代表大会，是在全党全国各族人民迈上全面建设社会主义现代化国家新征程、向第二个百年奋斗目标进军的关键时刻召开的一次十分重要的大会。大会高举的伟大旗帜是（    ）",
        "content": [
          "A. 贯彻新发展理念\tB. 全面推进乡村振兴",
          "C. 推动高质量发展\tD. 中国特色社会主义"
        ]
      },
      {
        "title": "2. 在某校心理游园会的“微笑欢迎你”驿站，同学们制作果蔬笑脸，画出自己的微笑卡，将自己的“坏情绪”写在卡片上丢进“情绪回收站”，微笑着在满是笑脸的背景墙前拍照留念……这些活动旨在引导学生（    ）",
        "content": [
          "①学会调节情绪，化解烦恼   ②尊重他人感受，关爱自己",
          "③保持积极心态，健康生活   ④避免负面情绪，传递温暖",
          "A. ①②\tB. ①③\tC. ②④\tD. ③④"
        ]
      },
      {
        "title": "3. 小强和小军是好朋友，两个人都是校乒乓球队主力。",
        "content": [
          "他们的对话启示我们（    ）",
          "①友谊在竞争中得到升华、深化   ②要想了解自己，最好问问别人",
          "③集体成员交流互鉴，共同进步   ④集体要承认个人利益的合理性",
          "A. ①③\tB. ①④\tC. ②③\tD. ②④"
        ]
      },
      {
        "title": "4. 打开手机软件，系统自动读屏，并一一给出语音提示。看新闻，靠文字识别技术“读”出资讯；想购物，图片转语音“描绘”商品详情……借助信息无障碍技术，视障者可以在工作、生活中，更好地使用互联网产品。这说明（    ）",
        "content": [
          "A. 网络为经济发展注入新的活力",
          "B. 网络丰富日常生活，“信息节食”很重要",
          "C. 技术使网络环境更加便利、包容、温暖",
          "D. 信息无障碍建设成为各行业的自觉行动"
        ]
      },
      {
        "title": "5. 社会生活离不开规则。有同学说，规则像道路上的斑马线，像悬崖边上的护栏，像过山车上的安全带。这一说法启示我们（    ）",
        "content": [
          "①规则划定自由的边界，是自由的保障     ②违反规则就会受到法律的制裁",
          "③规则是在人们达成共识基础上形成的     ④每个人要发自内心地敬畏规则",
          "A. ①②\tB. ①④\tC. ②③\tD. ③④"
        ]
      }
    ]
  },
  {
    "filename": "2019年北京市中考道德与法治真题（空白卷）.docx",
    "subject": "政治",
    "year": 2019,
    "questions": [
      {
        "title": "1. 2019年是新中国成立70周年,是全面建成小康社会、实现第一个百年奋斗目标的关键之年。2019年也是",
        "content": [
          "①澳门回归20周年",
          "②五四运动100周年",
          "③改革开放40周年",
          "④马克思诞辰200周年",
          "A.①②  B.①④  C.②③   D.③④"
        ]
      },
      {
        "title": "2.2018年12月8门，伴随着巨大的火箭爰鸣，肩负着亿万中华儿女的探月飞天梦想,我国在西昌卫星发射中心用长征三号乙运载火箭成功发射___探测器，开启，月球探测的新旅程，最终实现人类在月球背面软着陆，实现月球背面与地球之间的中继通信。",
        "content": [
          "A.嫦娥四号\tB.天舟一号C.墨子号\tD.天宫二号",
          "3,应急车道，是专门供工程救险、消防救援、医疗救护或民警执行紧急公务等处理应急事务车辆使用的车道，也被称为“生命通道”。我们要保持“生命通道”畅通，是因为",
          "A.生命是脆弱的，要自立自强",
          "B.要保障其他军道的行车速度",
          "C.生命至上，要保障及时救援",
          "D.生命是独特的，道路是不同的"
        ]
      },
      {
        "title": "4.《黄帝内经》中有“喜伤心、怒伤肝、忧伤肺、恐伤肾、思伤脾\"的记载，这启示我们",
        "content": [
          "①喜怒哀乐是人之常情  ②情绪与人的身心健康有关",
          "③要积极主动调控情绪  ④同一情绪对人的影响相同",
          "A.①② B.①④  C.②③ D.③④"
        ]
      },
      {
        "title": "5.图2给我们的启示是",
        "content": [
          "①面对诱惑要提高自控能力",
          "②努力奋斗就能够取得成功",
          "③面对挫折，态度不同结果可能会不同",
          "④面对挫折要保持乐观向上的积极心态",
          "A.①② B.①④ C.②③ D.③④"
        ]
      },
      {
        "title": "6.下面是一段关于友谊的故事。",
        "content": [
          "相识的那一年，他29岁，他39岁。一位情操高尚、平民情嫌、家国精怀，一位学识广博、光明磊落、真挚善良。一起工作的日子里，他们谈的是人民的疾苦与病病，说的是国家的前途与命运：分开的日子里，他们彼此惦念，友情并未随日月流逝而淡漠。他们的心，总是紧紧地连在一起……从中可以领悟到",
          "①桃李不言，下自成蹊②孤则易折，众则难摧③人之相知，贵在知心④志合者，不以山海为远",
          "A.①②B.①④ C.②③ D.③④"
        ]
      },
      {
        "title": "7.北京市政府整治城市顽疾,",
        "content": [
          "规范环境秩序，改善核心区背街小巷的环境面貌，让胡同成为有绿茵处、有鸟鸣声、有老北京氛围的清净舒适的公共空间，以新的形象展现首都风范、古都风韵和时代风貌。这些做法体现政府",
          "①关注民生，建设宜居的位活环境",
          "②坚持以生态文明建设为中心",
          "③作为权力机关要依法行使职权",
          "④不断满足人民对美好生活的向住",
          "A.①② B.①④ C.②③ D.③④"
        ]
      },
      {
        "title": "8.网上流传的一些名人名言并非真的出自名人之曰。最近，鲁迅博物馆资料查询在线检测系统上线，鲁迅是否说过相关词句，输入关键词一查便知，还能检索到其对应的文章出处。该查询系统的推出",
        "content": [
          "①有助于保护兽迅的名誉权",
          "②能够扩大社会上的名人效应",
          "③可以克服社会的浮躁心态",
          "④利于减少“伪名言”对公众的误导",
          "A.①②B.①④ C.②③ D.③④"
        ]
      },
      {
        "title": "9.图3给我们的警示是",
        "content": [
          "A.违反法律需要承担刑事责任",
          "B.面对冲突，未成年人要加强自我保护",
          "C.不良行为可能发展为犯罪，要防微杜渐",
          "D.遇到问题，要善用法律维护自己的权利"
        ]
      },
      {
        "title": "10.我国“十三五”期间脱贫攻坚的目标是，到2020年稳定实现农村贫困人口不愁吃、不愁穿，农村贫困人口义务教育、基本医疗、住房安全有保障。近年来，我国每年减贫超千万人，创造了人类减贫史上的奇迹。材料体现了我国",
        "content": [
          "①促进协调发展，增强人氏的获得感",
          "②坚持共享理念，全面实现了现代化",
          "③实现同步富裕，促进社会公平正义",
          "④尊重人权，保障公民发展权的实现",
          "A.①② B.①④ C.②③ D.③④"
        ]
      },
      {
        "title": "11.为了更好地保护非物质文化遗产，有市民给相关国家机关提了一些建议。下列建议中，应由全国人大及其常委会行使职权的是",
        "content": [
          "A.对侵犯非物质文化遗产知识产权的案件提起公诉",
          "B.直接打击侵犯非物质文化遗产知识产权的行为",
          "C.公开审理侵犯非物质文化遗产知识产权的案件",
          "D.加强对非物质文化遗产保护法实施情况的检查"
        ]
      }
    ]
  },
  {
    "filename": "2019年北京市中考道德与法治真题（解析卷）.docx",
    "subject": "政治",
    "year": 2019,
    "questions": [
      {
        "title": "1. 2019年是新中国成立70周年,是全面建成小康社会、实现第一个百年奋斗目标的关键之年。2019年也是",
        "content": [
          "①澳门回归20周年",
          "②五四运动100周年",
          "③改革开放40周年",
          "④马克思诞辰200周年",
          "A.①②  B.①④  C.②③   D.③④"
        ]
      },
      {
        "title": "2.2018年12月8门，伴随着巨大的火箭爰鸣，肩负着亿万中华儿女的探月飞天梦想,我国在西昌卫星发射中心用长征三号乙运载火箭成功发射___探测器，开启，月球探测的新旅程，最终实现人类在月球背面软着陆，实现月球背面与地球之间的中继通信。",
        "content": [
          "A.嫦娥四号\tB.天舟一号C.墨子号\tD.天宫二号",
          "3,应急车道，是专门供工程救险、消防救援、医疗救护或民警执行紧急公务等处理应急事务车辆使用的车道，也被称为“生命通道”。我们要保持“生命通道”畅通，是因为",
          "A.生命是脆弱的，要自立自强",
          "B.要保障其他军道的行车速度",
          "C.生命至上，要保障及时救援",
          "D.生命是独特的，道路是不同的"
        ]
      },
      {
        "title": "4.《黄帝内经》中有“喜伤心、怒伤肝、忧伤肺、恐伤肾、思伤脾\"的记载，这启示我们",
        "content": [
          "①喜怒哀乐是人之常情  ②情绪与人的身心健康有关",
          "③要积极主动调控情绪  ④同一情绪对人的影响相同",
          "A.①② B.①④  C.②③ D.③④"
        ]
      },
      {
        "title": "5.图2给我们的启示是",
        "content": [
          "①面对诱惑要提高自控能力",
          "②努力奋斗就能够取得成功",
          "③面对挫折，态度不同结果可能会不同",
          "④面对挫折要保持乐观向上的积极心态",
          "A.①② B.①④ C.②③ D.③④"
        ]
      },
      {
        "title": "6.下面是一段关于友谊的故事。",
        "content": [
          "相识的那一年，他29岁，他39岁。一位情操高尚、平民情嫌、家国精怀，一位学识广博、光明磊落、真挚善良。一起工作的日子里，他们谈的是人民的疾苦与病病，说的是国家的前途与命运：分开的日子里，他们彼此惦念，友情并未随日月流逝而淡漠。他们的心，总是紧紧地连在一起……从中可以领悟到",
          "①桃李不言，下自成蹊②孤则易折，众则难摧③人之相知，贵在知心④志合者，不以山海为远",
          "A.①②B.①④ C.②③ D.③④"
        ]
      },
      {
        "title": "7.北京市政府整治城市顽疾,",
        "content": [
          "规范环境秩序，改善核心区背街小巷的环境面貌，让胡同成为有绿茵处、有鸟鸣声、有老北京氛围的清净舒适的公共空间，以新的形象展现首都风范、古都风韵和时代风貌。这些做法体现政府",
          "①关注民生，建设宜居的位活环境",
          "②坚持以生态文明建设为中心",
          "③作为权力机关要依法行使职权",
          "④不断满足人民对美好生活的向住",
          "A.①② B.①④ C.②③ D.③④"
        ]
      },
      {
        "title": "8.网上流传的一些名人名言并非真的出自名人之曰。最近，鲁迅博物馆资料查询在线检测系统上线，鲁迅是否说过相关词句，输入关键词一查便知，还能检索到其对应的文章出处。该查询系统的推出",
        "content": [
          "①有助于保护兽迅的名誉权",
          "②能够扩大社会上的名人效应",
          "③可以克服社会的浮躁心态",
          "④利于减少“伪名言”对公众的误导",
          "A.①②B.①④ C.②③ D.③④"
        ]
      },
      {
        "title": "9.图3给我们的警示是",
        "content": [
          "A.违反法律需要承担刑事责任",
          "B.面对冲突，未成年人要加强自我保护",
          "C.不良行为可能发展为犯罪，要防微杜渐",
          "D.遇到问题，要善用法律维护自己的权利"
        ]
      },
      {
        "title": "10.我国“十三五”期间脱贫攻坚的目标是，到2020年稳定实现农村贫困人口不愁吃、不愁穿，农村贫困人口义务教育、基本医疗、住房安全有保障。近年来，我国每年减贫超千万人，创造了人类减贫史上的奇迹。材料体现了我国",
        "content": [
          "①促进协调发展，增强人氏的获得感",
          "②坚持共享理念，全面实现了现代化",
          "③实现同步富裕，促进社会公平正义",
          "④尊重人权，保障公民发展权的实现",
          "A.①② B.①④ C.②③ D.③④"
        ]
      },
      {
        "title": "11.为了更好地保护非物质文化遗产，有市民给相关国家机关提了一些建议。下列建议中，应由全国人大及其常委会行使职权的是",
        "content": [
          "A.对侵犯非物质文化遗产知识产权的案件提起公诉",
          "B.直接打击侵犯非物质文化遗产知识产权的行为",
          "C.公开审理侵犯非物质文化遗产知识产权的案件",
          "D.加强对非物质文化遗产保护法实施情况的检查"
        ]
      }
    ]
  },
  {
    "filename": "2024年北京市中考道德与法治真题（空白卷）.docx",
    "subject": "政治",
    "year": 2024,
    "questions": [
      {
        "title": "1．本试卷共8页，共两部分，共20题，满分70分。考试时间70分钟",
        "content": []
      },
      {
        "title": "2．在试卷和草稿纸上准确填写姓名、准考证号、考场号和座位号。",
        "content": []
      },
      {
        "title": "3．试题答案一律填涂或书写在答题卡上，在试卷上作答无效。",
        "content": []
      },
      {
        "title": "4．在答题卡上，选择题用2B铅笔作答，其他试题用黑色字迹签字笔作答。",
        "content": []
      },
      {
        "title": "5．考试结束，将本试卷、答题卡和草稿纸一并交回。",
        "content": [
          "第一部分",
          "本部分共15题，每题2分，共30分。在每题列出的四个选项中，选出最符合题目要求的一项。"
        ]
      },
      {
        "title": "1. 2024年1月19日，“____”表彰大会在北京召开。这是党中央、国务院首次对这一奖项开展评选表彰。获奖个人和团队不断突破关键核心技术，取得一批先进技术成果，为加快实现高水平科技自立自强作出突出贡献。（   ）",
        "content": [
          "A. 共和国勋章\tB. 人民楷模\tC. 国家工程师奖\tD. 中国青年五四奖章"
        ]
      },
      {
        "title": "2. 某班开展“我的自画像”活动，两位同学交流了他们的想法。",
        "content": [
          "以上对话告诉我们（   ）",
          "A. 生命是独特的，要关心身边每一个人",
          "B. 可通过自我评价和他人评价认识自己",
          "C. 要加强沟通，以同学们的意见为标尺",
          "D 情绪会相互感染，要用恰当方式表达"
        ]
      },
      {
        "title": "3. “青春”一词来自《楚辞》，意为万物葱郁，青绿茂盛之时。有人说，青春蕴含无穷潜能，青春孕育无限希望，青春追求光辉的理想，青春奋进的步伐永不停息，这告诉我们要（   ）",
        "content": [
          "A. 己所不欲，勿施于人\tB. 施惠毋念，受恩莫忘",
          "C. 功崇惟志，业广惟勤\tD. 求同存异，以礼待人"
        ]
      },
      {
        "title": "4. “白天上班，晚上学艺”，上夜校正在成为青年人新生活方式。青年夜校有非遗制作、电影鉴赏、录制编辑、人工智能等课程，为青年人提供了多样的休闲生活和发展可能。上夜校有助于青年人（   ）",
        "content": [
          "①加强学习，不断提升自身素质②释放压力，避免负面情感产生",
          "③编织梦想，防止未来遇到挫折④充盈生命，丰富人生阅历体验",
          "A. ①②\tB. ①④\tC. ②③\tD. ③④"
        ]
      },
      {
        "title": "5. 交通警察走进校园开展“交通安全”普法活动，宣讲了以下内容。",
        "content": [
          "交通警察的宣讲让我们认识到（   ）",
          "①上述行为是不负责任的行为，需要社会成员共同执法",
          "②上述行为属于一般违法行为，需要承担刑事责任",
          "③要珍爱生命，增强道路交通安全意识",
          "④要发自内心地尊崇法律，自觉规范行为",
          "A. ①②\tB. ①④\tC. ②③\tD. ③④"
        ]
      }
    ]
  },
  {
    "filename": "2023年北京市中考道德与法治真题（解析卷）.docx",
    "subject": "政治",
    "year": 2023,
    "questions": [
      {
        "title": "1．本试卷共8页，共两部分，共20题，满分70分。考试时间70分钟。",
        "content": []
      },
      {
        "title": "2．在试卷和草稿纸上准确填写姓名、准考证号、考场号和座位号。",
        "content": []
      },
      {
        "title": "3．试题答案一律填涂或书写在答题卡上，在试卷上作答无效。",
        "content": []
      },
      {
        "title": "4．在答题卡上，选择题用2B铅笔作答，其他试题用黑色字迹签字笔作答。",
        "content": []
      },
      {
        "title": "5．考试结束，将本试卷、答题卡和草稿纸一并交回。",
        "content": [
          "第一部分",
          "本部分共15题，每题2分，共30分。在每题列出的四个选项中，选出最符合题目要求的一项。"
        ]
      },
      {
        "title": "1. 中国共产党第二十次全国代表大会，是在全党全国各族人民迈上全面建设社会主义现代化国家新征程、向第二个百年奋斗目标进军的关键时刻召开的一次十分重要的大会。大会高举的伟大旗帜是（    ）",
        "content": [
          "A. 贯彻新发展理念\tB. 全面推进乡村振兴",
          "C. 推动高质量发展\tD. 中国特色社会主义",
          "【答案】D",
          "【解析】",
          "【详解】时政题，解析略。"
        ]
      },
      {
        "title": "2. 在某校心理游园会的“微笑欢迎你”驿站，同学们制作果蔬笑脸，画出自己的微笑卡，将自己的“坏情绪”写在卡片上丢进“情绪回收站”，微笑着在满是笑脸的背景墙前拍照留念……这些活动旨在引导学生（    ）",
        "content": [
          "①学会调节情绪，化解烦恼   ②尊重他人感受，关爱自己",
          "③保持积极心态，健康生活   ④避免负面情绪，传递温暖",
          "A. ①②\tB. ①③\tC. ②④\tD. ③④",
          "【答案】B",
          "【解析】",
          "【详解】本题考查调节情绪。",
          "①③：同学们将自己的“坏情绪”写在卡片上丢进“情绪回收站”，引导学生学会调节情绪，化解烦恼 ，并且保持积极心态，健康生活，故 ①③符合题意；",
          "②：材料未体现尊重他人感受，关爱自己，故②不符合题意；",
          "④：不用避免负面情绪，要学会调节负面情绪，负面情绪对我们成长也有意义，故④说法错误；",
          "故本题选B。"
        ]
      },
      {
        "title": "3. 小强和小军是好朋友，两个人都是校乒乓球队的主力。",
        "content": [
          "他们的对话启示我们（    ）",
          "①友谊在竞争中得到升华、深化   ②要想了解自己，最好问问别人",
          "③集体成员交流互鉴，共同进步   ④集体要承认个人利益的合理性",
          "A. ①③\tB. ①④\tC. ②③\tD. ②④",
          "【答案】A",
          "【解析】",
          "【详解】本题考查正确认识友谊、美好集体的特征。",
          "①③：从小强和小军的对话中我们可以感受到竞争并不必然伤害友谊，启示我们友谊可以在竞争中得到升华、深化；也启示我们在集体生活中，集体成员之间交流互鉴，合作学习，共同提高，①③说法正确；",
          "②：体现的是认识自己的方法，②说法与题不符；",
          "④：体现的是正确处理集体利益和个人利益的关系，④说法与题不符；",
          "故本题选A。"
        ]
      },
      {
        "title": "4. 打开手机软件，系统自动读屏，并一一给出语音提示。看新闻，靠文字识别技术“读”出资讯；想购物，图片转语音“描绘”商品详情……借助信息无障碍技术，视障者可以在工作、生活中，更好地使用互联网产品。这说明（    ）",
        "content": [
          "A. 网络为经济发展注入新的活力",
          "B. 网络丰富日常生活，“信息节食”很重要",
          "C. 技术使网络环境更加便利、包容、温暖",
          "D. 信息无障碍建设成为各行业的自觉行动",
          "【答案】C",
          "【解析】",
          "【详解】本题考查创新让生活更美好。",
          "C：分析题文，自动读屏、语音提示、文字识别、图片转语音、信息无障碍技术等，结合所学知识可知，这说明技术使网络环境更加便利、包容、温暖；C正确；",
          "A：题干没有体现网络为经济发展注入新的活力；A不符合题意；",
          "B：“信息节食”在 题干中没有体现；B不符合题意；",
          "D：信息无障碍建设并没有成为各行业的自觉行动；D错误；",
          "故本题选C。"
        ]
      },
      {
        "title": "5. 社会生活离不开规则。有同学说，规则像道路上的斑马线，像悬崖边上的护栏，像过山车上的安全带。这一说法启示我们（    ）",
        "content": [
          "①规则划定自由的边界，是自由的保障     ②违反规则就会受到法律的制裁",
          "③规则是在人们达成共识基础上形成的     ④每个人要发自内心地敬畏规则",
          "A. ①②\tB. ①④\tC. ②③\tD. ③④",
          "【答案】B",
          "【解析】",
          "【详解】本题考查遵守规则",
          "①④：分析题文，规则像道路上的斑马线，像悬崖边上的护栏，像过山车上的安全带，这启示我们每个人要发自内心地敬畏规则；规则划定自由的边界，是自由的保障；①④符合题意；",
          "②：违反法律规则就会受到法律的制裁，②错误；",
          "③：不符合题干主旨；③不符合题意；",
          "故本题选B。"
        ]
      }
    ]
  },
  {
    "filename": "2024年北京市中考道德与法治真题（解析卷）.docx",
    "subject": "政治",
    "year": 2024,
    "questions": [
      {
        "title": "1．本试卷共8页，共两部分，共20题，满分70分。考试时间70分钟",
        "content": []
      },
      {
        "title": "2．在试卷和草稿纸上准确填写姓名、准考证号、考场号和座位号。",
        "content": []
      },
      {
        "title": "3．试题答案一律填涂或书写在答题卡上，在试卷上作答无效。",
        "content": []
      },
      {
        "title": "4．在答题卡上，选择题用2B铅笔作答，其他试题用黑色字迹签字笔作答。",
        "content": []
      },
      {
        "title": "5．考试结束，将本试卷、答题卡和草稿纸一并交回。",
        "content": [
          "第一部分",
          "本部分共15题，每题2分，共30分。在每题列出的四个选项中，选出最符合题目要求的一项。"
        ]
      },
      {
        "title": "1. 2024年1月19日，“____”表彰大会在北京召开。这是党中央、国务院首次对这一奖项开展评选表彰。获奖个人和团队不断突破关键核心技术，取得一批先进技术成果，为加快实现高水平科技自立自强作出突出贡献。（   ）",
        "content": [
          "A. 共和国勋章\tB. 人民楷模\tC. 国家工程师奖\tD. 中国青年五四奖章",
          "【答案】C",
          "【解析】",
          "【详解】本题考查时政，解析略。"
        ]
      },
      {
        "title": "2. 某班开展“我的自画像”活动，两位同学交流了他们的想法。",
        "content": [
          "以上对话告诉我们（   ）",
          "A. 生命是独特的，要关心身边每一个人",
          "B. 可通过自我评价和他人评价认识自己",
          "C. 要加强沟通，以同学们的意见为标尺",
          "D. 情绪会相互感染，要用恰当方式表达",
          "【答案】B",
          "【解析】",
          "【详解】本题考查正确认识自己的方法、正确对待他人评价的方法。",
          "B：依据教材知识，分析题文，第一位同学通过关注自己的特点、记录内心活动和情绪表现来“画”出独特的自己，体现了自我评价；第二位同学通过主动倾听别人的意见，结合具体情况来“画”出全面的自己，体现了他人评价，这告诉我们可以通过自我评价和他人评价认识自己，故B符合题意；",
          "AD：题文未体现生命是独特的，要关心身边每一个人；情绪会相互感染，要用恰当方式表达，故AD不符合题意；",
          "C：同学们的意见未必准确，我们要有自己独到的见解，故C说法错误；",
          "故本题选B。"
        ]
      },
      {
        "title": "3. “青春”一词来自《楚辞》，意为万物葱郁，青绿茂盛之时。有人说，青春蕴含无穷潜能，青春孕育无限希望，青春追求光辉的理想，青春奋进的步伐永不停息，这告诉我们要（   ）",
        "content": [
          "A. 己所不欲，勿施于人\tB. 施惠毋念，受恩莫忘",
          "C. 功崇惟志，业广惟勤\tD. 求同存异，以礼待人",
          "【答案】C",
          "【解析】",
          "【详解】本题考查对青春的认识。",
          "C：青春追求光辉的理想，青春奋进的步伐永不停息，告诉我们要不断追求自己的梦想，不断让自己变得更好；功崇惟志，业广惟勤，意思是取得伟大的功业，是由于有伟大的志向，完成伟大的功业，在于辛勤不懈地工作，故C符合题意；",
          "A：己所不欲，勿施于人，意思是指自己不愿意的，不要施加给别人，告诉我们要学会换位思考，故A不符合题意；",
          "B：施惠毋念，受恩莫忘，意思是对人施了恩惠，不要记在心里，受了他人的恩惠，一定要常记在心，告诉我们要学会感恩，故B不符合题意；",
          "D：求同存异，意思是找出共同点，保留不同意见；以礼待人，意思是对人要有礼貌，告诉我们要宽容他人、做文明有礼的人，故D不符合题意；",
          "故本题选C。"
        ]
      },
      {
        "title": "4. “白天上班，晚上学艺”，上夜校正在成为青年人新的生活方式。青年夜校有非遗制作、电影鉴赏、录制编辑、人工智能等课程，为青年人提供了多样的休闲生活和发展可能。上夜校有助于青年人（   ）",
        "content": [
          "①加强学习，不断提升自身素质②释放压力，避免负面情感产生",
          "③编织梦想，防止未来遇到挫折④充盈生命，丰富人生阅历体验",
          "A. ①②\tB. ①④\tC. ②③\tD. ③④",
          "【答案】B",
          "【解析】",
          "【详解】本题考查学习的意义、充盈生命。",
          "①④：青年夜校为青年人提供了多样的休闲生活和发展可能，体现了上夜校对青年人的成长具有重要意义；依据教材知识可知，上夜校有助于青年人加强学习，不断提升自身素质，充盈生命，丰富人生阅历体验，故①④说法正确；",
          "②：负面情感难以避免，故②说法错误；",
          "③：人生难免有挫折，“防止未来遇到挫折”不现实，故③说法错误；",
          "故本题选B。"
        ]
      },
      {
        "title": "5. 交通警察走进校园开展“交通安全”普法活动，宣讲了以下内容。",
        "content": [
          "交通警察的宣讲让我们认识到（   ）",
          "①上述行为是不负责任的行为，需要社会成员共同执法",
          "②上述行为属于一般违法行为，需要承担刑事责任",
          "③要珍爱生命，增强道路交通安全意识",
          "④要发自内心地尊崇法律，自觉规范行为",
          "A. ①②\tB. ①④\tC. ②③\tD. ③④",
          "【答案】D",
          "【解析】",
          "【详解】本题考查敬畏生命、树立法治意识。",
          "③④：驾驶机动车不得有拨打接听手持电话，观看电视等妨碍安全驾驶的行为；如果分心两秒钟，车辆就能驶出将近60米，容易发生危险；体现了安全驾驶的重要性；让我们认识到要珍爱生命，增强道路交通安全意识，要发自内心地尊崇法律，自觉规范行为，故③④说法正确；",
          "①：社会成员没有执法权，行政机关才有执法权，故①说法错误；",
          "②：题干中的行为如果造成严重后果的话，可能是犯罪，一般违法行为不需要承担刑事责任，故②说法错误；",
          "故本题选D。"
        ]
      }
    ]
  },
  {
    "filename": "2022年北京市中考道德与法治真题（空白卷）.docx",
    "subject": "政治",
    "year": 2022,
    "questions": [
      {
        "title": "1. 历经7年艰辛努力，北京冬奥会、冬残奥会胜利举办，举国关注，举世瞩目。北京冬奥会、冬残奥会广大参与者珍惜伟大时代赋予的机遇，在冬奥申办、筹办、举办的过程中，共同创造了北京冬奥精神。这一精神就是（）",
        "content": [
          "A. 追逐梦想、勇于探索、协同攻坚、合作共赢",
          "B. 胸怀大局、自信开放、迎难而上、追求卓越、共创未来",
          "C. 生命至上、举国同心、舍生忘死、尊重科学、命运与共",
          "D. 上下同心、尽锐出战、精准务实、开拓创新、攻坚克难、不负人民"
        ]
      },
      {
        "title": "2. 我们守护生命，既要爱护身体，又要养护精神。下列选项体现充盈精神世界的是（）",
        "content": [
          "①居家学习期间注意规律作息，适当锻炼②在学校的组织下一起收看“天宫课堂”",
          "③参加应急逃生演练，掌握自护自救技能④参加“书香中国·北京阅读季”主题活动",
          "A. ①②\tB. ①③\tC. ②④\tD. ③④"
        ]
      },
      {
        "title": "3. 认识自己很重要。下图启示我们（）",
        "content": [
          "①他人评价是认识自己的一面镜子②公开自己的秘密才能被别人接纳",
          "③我们需要不断地探索和发现自己④扩大盲目区有利于全面认识自己",
          "A. ①③\tB. ①④\tC. ②③\tD. ②④"
        ]
      },
      {
        "title": "4. “非淡泊无以明志，非宁静无以致远。”“非学无以广才，非志无以成学。”诸葛亮在《诫子书》中对儿子的这些教诲告诉我们（）",
        "content": [
          "①宽以待人，设身处地为他人着想②修身养性，明确自己的人生志向",
          "③转听教海，做到唯父母之命是从④发奋学习，提升个人能力和智慧",
          "A. ①③\tB. ①④\tC. ②③\tD. ②④"
        ]
      },
      {
        "title": "5. 一位老师每逢节气都会给学生写寄语，下面是其中的一部分。",
        "content": [
          "此举体现了（）",
          "①循循善诱，诲人不倦②因循守旧，固守传统",
          "③以文化人，润心启智④尊师重教，教学相长",
          "A. ①③\tB. ①④\tC. ②③\tD. ②④"
        ]
      },
      {
        "title": "6. 神舟十四号乘组的一位航天员说，作为战友，我们朝夕相处、并肩作战，共同经历了12年的学习和训练。我们是使命共同体、责任共同体、荣誉共同体。感谢教育培养我的广大科技人员，感谢航天员大队的全体战友。对这段话理解正确的是（）",
        "content": [
          "①在集体中应尊重和保护个人利益②勇于担当，维护集体荣誉和利益",
          "③共同愿景引领集体成员团结进取④美好集体应善于合作，敢于竞争",
          "A. ①③\tB. ①④\tC. ②③\tD. ②④"
        ]
      },
      {
        "title": "7. “先看病，先拿药，后支付。”北京某区推出信用医疗服务，市民可以凭借自己的“信用”在一定额度内，免除挂号、检查、检验、取药等多环节的排队缴费流程，实现医疗付费“零排队”。市民在医疗场景下的守信、失信记录会上传至全市公共信用信息服务平台。信用医疗服务的实施（）",
        "content": [
          "①方便市民就医，增进社会互信②说明企业诚信经营才能够赢得客户",
          "③引导市民珍惜个人的信用记录④表明格守诚信与保护隐私是对立的",
          "A. ①②\tB. ①③\tC. ②④\tD. ③④"
        ]
      },
      {
        "title": "8. “国家通过各种途径，创造劳动就业条件，加强劳动保护，改善劳动条件，并在发展生产的基础上，提高劳动报酬和福利待遇。”“劳动是一切有劳动能力的公民的光荣职责。”我国宪法的这些规定说明（）",
        "content": [
          "A. 应先行使权利后履行义务\tB. 放弃权利就可以不履行义务",
          "C. 权利和义务是完全对等的\tD. 有的权利同时也是义务"
        ]
      },
      {
        "title": "9. 某派出所民警是全国公安系统英模代表，她负责的辖区内居民老龄化程度较高，80岁以上的老人占17%。为了保护老人的生命财产安全，她带领同事们推行邻里守望结对子等工作机制，通过一键式呼救等方式为老人提供生活便利和安全保障。材料体现了（）",
        "content": [
          "①公安机关用忠诚担当守护百姓安宁幸福②协助和配合公安机关工作是公民的权利",
          "③公安机关创新工作方式，提高服务水平④公安机关自觉接受监督，防止权力滥用",
          "A. ①③\tB. ①④\tC. ②③\tD. ②④"
        ]
      },
      {
        "title": "10. 公民权利受到损害，要依照法定程序维护权利。诉讼是处理纠纷和应对侵害最正规，最权威的手段，是维护合法权益的最后屏障。下列属于诉讼的是（）",
        "content": [
          "A. 张某向消费者协会投诉某商场产品存在质量问题",
          "B. 市民王某向环保部门反映某企业的违法排污行为",
          "C. 某企业因拖欠员工工资被劳动保障行政部门调查",
          "D. 人民法院就郑某某侵害他人名誉权一案进行审理"
        ]
      }
    ]
  },
  {
    "filename": "2022年北京市中考道德与法治真题（解析卷）.docx",
    "subject": "政治",
    "year": 2022,
    "questions": [
      {
        "title": "1. 历经7年艰辛努力，北京冬奥会、冬残奥会胜利举办，举国关注，举世瞩目。北京冬奥会、冬残奥会广大参与者珍惜伟大时代赋予的机遇，在冬奥申办、筹办、举办的过程中，共同创造了北京冬奥精神。这一精神就是（）",
        "content": [
          "A. 追逐梦想、勇于探索、协同攻坚、合作共赢",
          "B. 胸怀大局、自信开放、迎难而上、追求卓越、共创未来",
          "C. 生命至上、举国同心、舍生忘死、尊重科学、命运与共",
          "D. 上下同心、尽锐出战、精准务实、开拓创新、攻坚克难、不负人民",
          "【参考答案】B"
        ]
      },
      {
        "title": "2. 我们守护生命，既要爱护身体，又要养护精神。下列选项体现充盈精神世界的是（）",
        "content": [
          "①居家学习期间注意规律作息，适当锻炼②在学校的组织下一起收看“天宫课堂”",
          "③参加应急逃生演练，掌握自护自救技能④参加“书香中国·北京阅读季”主题活动",
          "A. ①②\tB. ①③\tC. ②④\tD. ③④",
          "【参考答案】C"
        ]
      },
      {
        "title": "3. 认识自己很重要。下图启示我们（）",
        "content": [
          "①他人评价是认识自己的一面镜子②公开自己的秘密才能被别人接纳",
          "③我们需要不断地探索和发现自己④扩大盲目区有利于全面认识自己",
          "A. ①③\tB. ①④\tC. ②③\tD. ②④",
          "【参考答案】A"
        ]
      },
      {
        "title": "4. “非淡泊无以明志，非宁静无以致远。”“非学无以广才，非志无以成学。”诸葛亮在《诫子书》中对儿子的这些教诲告诉我们（）",
        "content": [
          "①宽以待人，设身处地为他人着想②修身养性，明确自己的人生志向",
          "③转听教海，做到唯父母之命是从④发奋学习，提升个人能力和智慧",
          "A. ①③\tB. ①④\tC. ②③\tD. ②④",
          "【参考答案】D"
        ]
      },
      {
        "title": "5. 一位老师每逢节气都会给学生写寄语，下面是其中的一部分。",
        "content": [
          "此举体现了（）",
          "①循循善诱，诲人不倦②因循守旧，固守传统",
          "③以文化人，润心启智④尊师重教，教学相长",
          "A. ①③\tB. ①④\tC. ②③\tD. ②④",
          "【参考答案】A"
        ]
      },
      {
        "title": "6. 神舟十四号乘组的一位航天员说，作为战友，我们朝夕相处、并肩作战，共同经历了12年的学习和训练。我们是使命共同体、责任共同体、荣誉共同体。感谢教育培养我的广大科技人员，感谢航天员大队的全体战友。对这段话理解正确的是（）",
        "content": [
          "①在集体中应尊重和保护个人利益②勇于担当，维护集体荣誉和利益",
          "③共同愿景引领集体成员团结进取④美好集体应善于合作，敢于竞争",
          "A. ①③\tB. ①④\tC. ②③\tD. ②④",
          "【参考答案】C"
        ]
      },
      {
        "title": "7. “先看病，先拿药，后支付。”北京某区推出信用医疗服务，市民可以凭借自己的“信用”在一定额度内，免除挂号、检查、检验、取药等多环节的排队缴费流程，实现医疗付费“零排队”。市民在医疗场景下的守信、失信记录会上传至全市公共信用信息服务平台。信用医疗服务的实施（）",
        "content": [
          "①方便市民就医，增进社会互信②说明企业诚信经营才能够赢得客户",
          "③引导市民珍惜个人的信用记录④表明格守诚信与保护隐私是对立的",
          "A. ①②\tB. ①③\tC. ②④\tD. ③④",
          "【参考答案】B"
        ]
      },
      {
        "title": "8. “国家通过各种途径，创造劳动就业条件，加强劳动保护，改善劳动条件，并在发展生产的基础上，提高劳动报酬和福利待遇。”“劳动是一切有劳动能力的公民的光荣职责。”我国宪法的这些规定说明（）",
        "content": [
          "A. 应先行使权利后履行义务\tB. 放弃权利就可以不履行义务",
          "C. 权利和义务是完全对等的\tD. 有的权利同时也是义务",
          "【参考答案】D"
        ]
      },
      {
        "title": "9. 某派出所民警是全国公安系统英模代表，她负责的辖区内居民老龄化程度较高，80岁以上的老人占17%。为了保护老人的生命财产安全，她带领同事们推行邻里守望结对子等工作机制，通过一键式呼救等方式为老人提供生活便利和安全保障。材料体现了（）",
        "content": [
          "①公安机关用忠诚担当守护百姓安宁幸福②协助和配合公安机关工作是公民的权利",
          "③公安机关创新工作方式，提高服务水平④公安机关自觉接受监督，防止权力滥用",
          "A. ①③\tB. ①④\tC. ②③\tD. ②④",
          "【参考答案】A"
        ]
      },
      {
        "title": "10. 公民权利受到损害，要依照法定程序维护权利。诉讼是处理纠纷和应对侵害最正规，最权威的手段，是维护合法权益的最后屏障。下列属于诉讼的是（）",
        "content": [
          "A. 张某向消费者协会投诉某商场产品存在质量问题",
          "B. 市民王某向环保部门反映某企业的违法排污行为",
          "C. 某企业因拖欠员工工资被劳动保障行政部门调查",
          "D. 人民法院就郑某某侵害他人名誉权一案进行审理",
          "【参考答案】D"
        ]
      }
    ]
  },
  {
    "filename": "2021年北京市中考化学真题（空白卷）.docx",
    "subject": "化学",
    "year": 2021,
    "questions": [
      {
        "title": "1. 空气的成分中，体积分数约占78%的是",
        "content": [
          "A. 氮气\tB. 氧气\tC. 二氧化碳\tD. 稀有气体"
        ]
      },
      {
        "title": "2. 下列物质在O2中燃烧，火星四射，生成黑色固体的是",
        "content": [
          "A. 木炭\tB. 镁条\tC. 蜡烛\tD. 铁丝"
        ]
      },
      {
        "title": "3. 将CO2通入下列液体中，能产生白色沉淀的是",
        "content": [
          "A. 水\tB. 稀硫酸\tC. 食盐水\tD. 澄清石灰水"
        ]
      },
      {
        "title": "4. 下列物质能用作氮肥的是",
        "content": [
          "A. KCl\tB. K2CO3\tC. NH4Cl\tD. Ca3（PO4）2"
        ]
      },
      {
        "title": "5. 下列物质属于氧化物的是",
        "content": [
          "A. O2\tB. CaO\tC. H2SO4\tD. KMnO2"
        ]
      },
      {
        "title": "6. 下列仪器不能加热的是",
        "content": [
          "A. 烧杯\tB. 试管\tC. 量筒\tD. 燃烧匙"
        ]
      },
      {
        "title": "7. 下列物质含有氢分子的是",
        "content": [
          "A. Ca（OH）2\tB. H2CO3\tC. H2O2\tD. H2"
        ]
      },
      {
        "title": "8. 下列物质能除铁锈的是",
        "content": [
          "A. 盐酸\tB. 植物油\tC. NaOH溶液\tD. 食盐水"
        ]
      },
      {
        "title": "9. 电解水实验如图，下列说法不正确的是",
        "content": [
          "A. 试管1中得到H2\tB. 水由H2、O2构成",
          "C. 水发生了分解反应\tD. 水由氢、氧元素组成"
        ]
      },
      {
        "title": "10. 下列元素中，人体摄入过低会引起贫血的是",
        "content": [
          "A. 铁\tB. 碘\tC. 锌\tD. 钙"
        ]
      }
    ]
  },
  {
    "filename": "2022年北京市中考化学真题（空白卷）.docx",
    "subject": "化学",
    "year": 2022,
    "questions": [
      {
        "title": "1. 下列自行车构件及配件所用的材料中，属于金属材料的是",
        "content": [
          "A. 塑料车筐\tB. 橡胶车胎\tC. 钢制车圈\tD. 棉布座套"
        ]
      },
      {
        "title": "2. 下列生活用品，利用金属导电性的是",
        "content": [
          "A. 铁锅\tB. 铜导线\tC. 铝箔包装纸\tD. 金饰品"
        ]
      },
      {
        "title": "3. 一些食物的pH范围如下，其中酸性最强的是",
        "content": [
          "A. 橘子汁(3-4)\tB. 西瓜汁(5-6)\tC. 牛奶(6~7)\tD. 鸡蛋清(7~8)"
        ]
      },
      {
        "title": "4. 垃圾分类人人有责。香蕉皮属于",
        "content": [
          "A. 可回收物\tB. 其他垃圾\tC. 厨余垃圾\tD. 有害垃圾"
        ]
      },
      {
        "title": "5. 人体每日需要摄入适量的钙，这里的“钙”指的是",
        "content": [
          "A. 元素\tB. 单质\tC. 分子\tD. 原子"
        ]
      },
      {
        "title": "6. 化肥对提高农作物的产量具有重要作用。下列物质能用作钾肥的是",
        "content": [
          "A. K2SO4\tB. CO(NH2)2\tC. NH4Cl\tD. Ca(H2PO4)2"
        ]
      },
      {
        "title": "7. 化石燃料是不可再生的能源，下列不属于化石燃料的是",
        "content": [
          "A. 煤\tB. 石油\tC. 乙醇\tD. 天然气"
        ]
      },
      {
        "title": "8. 赤铁矿(主要成分是Fe2O3)用于工业炼铁。Fe2O3中铁元素的化合价为",
        "content": [
          "A. -3\tB. -2\tC. +2\tD. +3"
        ]
      },
      {
        "title": "9. 下列灭火措施不正确的是",
        "content": [
          "A. 森林起火，开辟隔离带\tB. 电线老化短路起火、用水浇灭",
          "C. 炒菜时油锅中的油不慎着火，用锅盖盖灭\tD. 酒精灯洒出的酒精在桌上燃烧，用湿布盖灭",
          "氧在自然界中广泛存在。回答下列3个小题。"
        ]
      },
      {
        "title": "10. 空气中氧气的体积分数约为（　　）",
        "content": [
          "A. 78%\tB. 21%\tC. 0.94%\tD. 0.03%"
        ]
      }
    ]
  }
]